super_pycocotools/__init__.py
super_pycocotools/coco.py
super_pycocotools/detectron.py
super_pycocotools-0.0.4.dist-info/METADATA
super_pycocotools-0.0.4.dist-info/WHEEL
super_pycocotools-0.0.4.dist-info/licenses/LICENSE
super_pycocotools-0.0.4.dist-info/RECORD
